QGraphViz/QGraphViz.py
QGraphViz/__init__.py
QGraphViz/DotParser/DotParser.py
QGraphViz/DotParser/Edge.py
QGraphViz/DotParser/Graph.py
QGraphViz/DotParser/Node.py
QGraphViz/DotParser/__init__.py
QGraphViz/Engines/Dot.py
QGraphViz/Engines/LayoutEngine.py
QGraphViz/Engines/__init__.py
QGraphViz-0.0.55.dist-info/LICENSE
QGraphViz-0.0.55.dist-info/METADATA
QGraphViz-0.0.55.dist-info/WHEEL
QGraphViz-0.0.55.dist-info/top_level.txt
QGraphViz-0.0.55.dist-info/RECORD
