Metadata-Version: 2.1
Name: QGraphViz
Version: 0.0.55
Summary: A PyQt5 widget to manipulate (build, render, interact, load and save) Graphviz graphs
Home-page: https://github.com/ParisNeo/QGraphViz
Author: Saifeddine ALOUI
Author-email: aloui.saifeddine@gmail.com
License: UNKNOWN
Platform: UNKNOWN
Classifier: Programming Language :: Python :: 3
Classifier: License :: OSI Approved :: MIT License
Classifier: Operating System :: OS Independent
